azureml/__init__.py
azureml/acft/__init__.py
azureml/acft/accelerator/NOTICE
azureml/acft/accelerator/__init__.py
azureml/acft/accelerator/_version.py
azureml/acft/accelerator/constants.py
azureml/acft/accelerator/finetune.py
azureml/acft/accelerator/lora_wrapper/__init__.py
azureml/acft/accelerator/lora_wrapper/lora_layers.py
azureml/acft/accelerator/lora_wrapper/lora_wrapper.py
azureml/acft/accelerator/lora_wrapper/peft_lora_wrapper.py
azureml/acft/accelerator/lora_wrapper/lora_configs/__init__.py
azureml/acft/accelerator/lora_wrapper/lora_configs/lora_bart.py
azureml/acft/accelerator/lora_wrapper/lora_configs/lora_base.py
azureml/acft/accelerator/lora_wrapper/lora_configs/lora_bert.py
azureml/acft/accelerator/lora_wrapper/lora_configs/lora_bert_base_uncased.py
azureml/acft/accelerator/lora_wrapper/lora_configs/lora_camembert.py
azureml/acft/accelerator/lora_wrapper/lora_configs/lora_deberta.py
azureml/acft/accelerator/lora_wrapper/lora_configs/lora_deberta_base.py
azureml/acft/accelerator/lora_wrapper/lora_configs/lora_distilbert.py
azureml/acft/accelerator/lora_wrapper/lora_configs/lora_distilbert_base_uncased.py
azureml/acft/accelerator/lora_wrapper/lora_configs/lora_falcon.py
azureml/acft/accelerator/lora_wrapper/lora_configs/lora_gpt2.py
azureml/acft/accelerator/lora_wrapper/lora_configs/lora_gpt_neox.py
azureml/acft/accelerator/lora_wrapper/lora_configs/lora_llama.py
azureml/acft/accelerator/lora_wrapper/lora_configs/lora_mbart.py
azureml/acft/accelerator/lora_wrapper/lora_configs/lora_roberta.py
azureml/acft/accelerator/lora_wrapper/lora_configs/lora_roberta_base.py
azureml/acft/accelerator/lora_wrapper/lora_configs/lora_t5.py
azureml/acft/accelerator/lora_wrapper/lora_configs/lora_turing_nlr_v3_cased.py
azureml/acft/accelerator/utils/__init__.py
azureml/acft/accelerator/utils/callbacks.py
azureml/acft/accelerator/utils/checkpoint_utils.py
azureml/acft/accelerator/utils/code_utils.py
azureml/acft/accelerator/utils/config.py
azureml_acft_accelerator-47.0.0.dist-info/LICENSE.txt
azureml_acft_accelerator-47.0.0.dist-info/METADATA
azureml_acft_accelerator-47.0.0.dist-info/WHEEL
azureml_acft_accelerator-47.0.0.dist-info/top_level.txt
azureml_acft_accelerator-47.0.0.dist-info/RECORD
