Metadata-Version: 2.1
Name: azureml-acft-accelerator
Version: 47.0.0
Summary: Contains the acft accelerator package used in script to build the azureml components.
Home-page: 
Author: Microsoft Corp
License: inline_license
Classifier: Development Status :: 3 - Alpha
Classifier: Intended Audience :: Developers
Classifier: Intended Audience :: Science/Research
Classifier: License :: Other/Proprietary License
Classifier: Programming Language :: Python :: 3.7
Classifier: Programming Language :: Python :: 3.8
Classifier: Programming Language :: Python :: 3.9
Classifier: Programming Language :: Python :: 3.10
Classifier: Programming Language :: Python :: 3.11
Classifier: Topic :: Scientific/Engineering :: Artificial Intelligence
Classifier: Operating System :: Microsoft :: Windows
Classifier: Operating System :: MacOS
Classifier: Operating System :: POSIX :: Linux
Requires-Python: >=3.7,<3.12
License-File: LICENSE.txt
Requires-Dist: azureml-core
Requires-Dist: azureml-automl-core
Requires-Dist: sentencepiece >=0.1.96
Requires-Dist: transformers >=4.26.1
Requires-Dist: optimum >=1.8.8
Requires-Dist: accelerate >=0.21.0
Requires-Dist: peft >=0.4.0
Provides-Extra: dev
Requires-Dist: twine ==3.3.0 ; extra == 'dev'
Requires-Dist: wheel ==0.37.0 ; extra == 'dev'
Provides-Extra: test
Requires-Dist: pytest ~=5.3.0 ; extra == 'test'
